evoclearn/core/VocalTractLabApi.so
evoclearn/core/__init__.py
evoclearn/core/definitions.py
evoclearn/core/distance.py
evoclearn/core/dtw.py
evoclearn/core/features.py
evoclearn/core/filters.py
evoclearn/core/io.py
evoclearn/core/log.py
evoclearn/core/mappings.py
evoclearn/core/qta.py
evoclearn/core/sequence.py
evoclearn/core/track.py
evoclearn/core/utils.py
evoclearn/core/version.py
evoclearn/core/vocaltractlab.py
evoclearn/core/cli/__init__.py
evoclearn/core/cli/filter.py
evoclearn/core/cli/map.py
evoclearn/core/cli/sample.py
evoclearn/core/constraints/__init__.py
evoclearn/core/constraints/generic.py
evoclearn/core/constraints/simple.py
evoclearn/core/samplers/__init__.py
evoclearn/core/samplers/tied_targets.py
evoclearn/core/samplers/uniform.py
evoclearn/core/samplers/uniform_problink.py
evoclearn_core-0.18.6.data/data/etc/JD2_bounds.json
evoclearn_core-0.18.6.data/data/etc/JD2_bounds_vowel-non-nasal.json
evoclearn_core-0.18.6.data/data/etc/JD2_speaker.xml
evoclearn_core-0.18.6.data/data/examples/advanced_constraints.ipynb
evoclearn_core-0.18.6.data/data/examples/building_bii.ipynb
evoclearn_core-0.18.6.data/data/examples/constraints.ipynb
evoclearn_core-0.18.6.data/data/examples/howto_sampling.ipynb
evoclearn_core-0.18.6.data/data/examples/sample_cvs.ipynb
evoclearn_core-0.18.6.data/data/examples/sample_vowels.ipynb
evoclearn_core-0.18.6.data/data/examples/synth_neutral.ipynb
evoclearn_core-0.18.6.data/data/examples/data/bad.TextGrid
evoclearn_core-0.18.6.data/data/examples/data/bad.wav
evoclearn_core-0.18.6.data/data/examples/data/bead.TextGrid
evoclearn_core-0.18.6.data/data/examples/data/bead.wav
evoclearn_core-0.18.6.data/data/examples/data/bii_vtlgui.txt
evoclearn_core-0.18.6.data/data/examples/data/bii_vtlgui.wav
evoclearn_core-0.18.6.data/data/examples/data/gO_from_presets.txt
evoclearn_core-0.18.6.dist-info/DESCRIPTION.rst
evoclearn_core-0.18.6.dist-info/METADATA
evoclearn_core-0.18.6.dist-info/RECORD
evoclearn_core-0.18.6.dist-info/WHEEL
evoclearn_core-0.18.6.dist-info/entry_points.txt
evoclearn_core-0.18.6.dist-info/metadata.json
evoclearn_core-0.18.6.dist-info/top_level.txt
